odoo9_addon_partner_ref_unique-9.0.1.0.0-py2.7-nspkg.pth
odoo9_addon_partner_ref_unique-9.0.1.0.0.dist-info/top_level.txt
odoo9_addon_partner_ref_unique-9.0.1.0.0.dist-info/WHEEL
odoo9_addon_partner_ref_unique-9.0.1.0.0.dist-info/RECORD
odoo9_addon_partner_ref_unique-9.0.1.0.0.dist-info/metadata.json
odoo9_addon_partner_ref_unique-9.0.1.0.0.dist-info/DESCRIPTION.rst
odoo9_addon_partner_ref_unique-9.0.1.0.0.dist-info/METADATA
odoo9_addon_partner_ref_unique-9.0.1.0.0.dist-info/namespace_packages.txt
odoo_addons/partner_ref_unique/__openerp__.py
odoo_addons/partner_ref_unique/__init__.py
odoo_addons/partner_ref_unique/README.rst
odoo_addons/partner_ref_unique/models/res_partner.py
odoo_addons/partner_ref_unique/models/__init__.py
odoo_addons/partner_ref_unique/models/res_company.py
odoo_addons/partner_ref_unique/views/res_company_view.xml
odoo_addons/partner_ref_unique/tests/__init__.py
odoo_addons/partner_ref_unique/tests/test_res_partner_ref.py
odoo_addons/partner_ref_unique/static/description/icon.png
